[
  {
    "Region": "AustraliaCentral",
    "VmSkus": [
      "basicAFamily",
      "standardA0_A7Family",
      "standardAv2Family",
      "standardBSFamily",
      "standardDDSv4Family",
      "standardDDv4Family",
      "standardDSv2Family",
      "standardDSv3Family",
      "standardDSv4Family",
      "standardDv2Family",
      "standardDv3Family",
      "standardDv4Family",
      "standardEDSv4Family",
      "standardEDv4Family",
      "standardEISv3Family",
      "standardEIv3Family",
      "standardESv3Family",
      "standardESv4Family",
      "standardEv3Family",
      "standardEv4Family",
      "standardFFamily",
      "standardFSFamily",
      "standardFSv2Family",
      "standardMSFamily",
      "standardXEIDSv4Family",
      "standardXEISv4Family"
    ]
  },
  {
    "Region": "AustraliaCentral2",
    "VmSkus": [
      "basicAFamily",
      "standardA0_A7Family",
      "standardAv2Family",
      "standardBSFamily",
      "standardDSv2Family",
      "standardDSv3Family",
      "standardDv2Family",
      "standardDv3Family",
      "standardEISv3Family",
      "standardEIv3Family",
      "standardESv3Family",
      "standardEv3Family",
      "standardFFamily",
      "standardFSFamily",
      "standardFSv2Family",
      "standardMSFamily"
    ]
  },
  {
    "Region": "australiaeast",
    "VmSkus": [
      "basicAFamily",
      "Standard NCASv3_T4 Family",
      "standardA0_A7Family",
      "standardAv2Family",
      "standardBSFamily",
      "standardDASv4Family",
      "standardDAv4Family",
      "standardDDSv4Family",
      "standardDDv4Family",
      "standardDFamily",
      "standardDSFamily",
      "standardDSv2Family",
      "standardDSv3Family",
      "standardDSv4Family",
      "standardDv2Family",
      "standardDv3Family",
      "standardDv4Family",
      "standardEASv4Family",
      "standardEAv4Family",
      "standardEDSv4Family",
      "standardEDv4Family",
      "standardEISv3Family",
      "standardEIv3Family",
      "standardESv3Family",
      "standardESv4Family",
      "standardEv3Family",
      "standardEv4Family",
      "standardFFamily",
      "standardFSFamily",
      "standardFSv2Family",
      "standardGFamily",
      "standardGSFamily",
      "standardHFamily",
      "standardLSFamily",
      "standardLSv2Family",
      "standardMDSmallv2Family",
      "standardMIDSmallv2Family",
      "standardMISmallv2Family",
      "standardMSFamily",
      "standardMSmallv2Family",
      "standardMSv2Family",
      "standardNCFamily",
      "standardNCSv3Family",
      "standardNVFamily",
      "standardNVSv2Family",
      "standardNVSv3Family",
      "standardNVSv4Family",
      "standardXEIDSv4Family",
      "standardXEISv4Family"
    ]
  },
  {
    "Region": "australiasoutheast",
    "VmSkus": [
      "basicAFamily",
      "standardA0_A7Family",
      "standardAv2Family",
      "standardBSFamily",
      "standardDDSv4Family",
      "standardDDv4Family",
      "standardDFamily",
      "standardDSFamily",
      "standardDSv2Family",
      "standardDSv3Family",
      "standardDSv4Family",
      "standardDv2Family",
      "standardDv3Family",
      "standardDv4Family",
      "standardEDSv4Family",
      "standardEDv4Family",
      "standardEISv3Family",
      "standardEIv3Family",
      "standardESv3Family",
      "standardESv4Family",
      "standardEv3Family",
      "standardEv4Family",
      "standardFFamily",
      "standardFSFamily",
      "standardFSv2Family",
      "standardMSFamily",
      "standardMSv2Family",
      "standardXEIDSv4Family",
      "standardXEISv4Family"
    ]
  },
  {
    "Region": "brazilsouth",
    "VmSkus": [
      "basicAFamily",
      "standardA0_A7Family",
      "standardAv2Family",
      "standardBSFamily",
      "standardDASv4Family",
      "standardDAv4Family",
      "standardDDSv4Family",
      "standardDDv4Family",
      "standardDFamily",
      "standardDSFamily",
      "standardDSv2Family",
      "standardDSv3Family",
      "standardDSv4Family",
      "standardDv2Family",
      "standardDv3Family",
      "standardDv4Family",
      "standardEASv4Family",
      "standardEAv4Family",
      "standardEDSv4Family",
      "standardEDv4Family",
      "standardEISv3Family",
      "standardEIv3Family",
      "standardESv3Family",
      "standardESv4Family",
      "standardEv3Family",
      "standardEv4Family",
      "standardFFamily",
      "standardFSFamily",
      "standardFSv2Family",
      "standardMSFamily",
      "standardMSv2Family",
      "standardNVSv2Family",
      "standardNVSv3Family",
      "standardXEIDSv4Family",
      "standardXEISv4Family"
    ]
  },
  {
    "Region": "BrazilSoutheast",
    "VmSkus": [
      "standardAv2Family",
      "standardBSFamily",
      "standardDDSv4Family",
      "standardDDv4Family",
      "standardDSv2Family",
      "standardDSv3Family",
      "standardDSv4Family",
      "standardDv2Family",
      "standardDv3Family",
      "standardDv4Family",
      "standardEDSv4Family",
      "standardEDv4Family",
      "standardESv3Family",
      "standardESv4Family",
      "standardEv3Family",
      "standardEv4Family",
      "standardFFamily",
      "standardFSFamily",
      "standardFSv2Family",
      "standardXEIDSv4Family",
      "standardXEISv4Family"
    ]
  },
  {
    "Region": "CanadaCentral",
    "VmSkus": [
      "basicAFamily",
      "standardA0_A7Family",
      "standardAv2Family",
      "standardBSFamily",
      "standardDCSv2Family",
      "standardDDSv4Family",
      "standardDDv4Family",
      "standardDSv2Family",
      "standardDSv3Family",
      "standardDSv4Family",
      "standardDv2Family",
      "standardDv3Family",
      "standardDv4Family",
      "standardEDSv4Family",
      "standardEDv4Family",
      "standardEISv3Family",
      "standardEIv3Family",
      "standardESv3Family",
      "standardESv4Family",
      "standardEv3Family",
      "standardEv4Family",
      "standardFFamily",
      "standardFSFamily",
      "standardFSv2Family",
      "standardGFamily",
      "standardGSFamily",
      "standardHBrsv2Family",
      "standardLSFamily",
      "standardMDSmallv2Family",
      "standardMIDSmallv2Family",
      "standardMISmallv2Family",
      "standardMSFamily",
      "standardMSmallv2Family",
      "standardNCSv3Family",
      "standardNVSv4Family",
      "standardXEIDSv4Family",
      "standardXEISv4Family"
    ]
  },
  {
    "Region": "CanadaEast",
    "VmSkus": [
      "basicAFamily",
      "standardA0_A7Family",
      "standardAv2Family",
      "standardBSFamily",
      "standardDCSv2Family",
      "standardDDSv4Family",
      "standardDDv4Family",
      "standardDSv2Family",
      "standardDSv3Family",
      "standardDSv4Family",
      "standardDv2Family",
      "standardDv3Family",
      "standardDv4Family",
      "standardEDSv4Family",
      "standardEDv4Family",
      "standardEISv3Family",
      "standardEIv3Family",
      "standardESv3Family",
      "standardESv4Family",
      "standardEv3Family",
      "standardEv4Family",
      "standardFFamily",
      "standardFSFamily",
      "standardFSv2Family",
      "standardGFamily",
      "standardGSFamily",
      "standardLSFamily",
      "standardMSFamily",
      "standardXEIDSv4Family",
      "standardXEISv4Family"
    ]
  },
  {
    "Region": "CentralIndia",
    "VmSkus": [
      "basicAFamily",
      "Standard NCASv3_T4 Family",
      "standardA0_A7Family",
      "standardAv2Family",
      "standardBSFamily",
      "standardDASv4Family",
      "standardDAv4Family",
      "standardDDSv4Family",
      "standardDDv4Family",
      "standardDFamily",
      "standardDSFamily",
      "standardDSv2Family",
      "standardDSv3Family",
      "standardDSv4Family",
      "standardDv2Family",
      "standardDv3Family",
      "standardDv4Family",
      "standardEASv4Family",
      "standardEAv4Family",
      "standardEDSv4Family",
      "standardEDv4Family",
      "standardEISv3Family",
      "standardEIv3Family",
      "standardESv3Family",
      "standardESv4Family",
      "standardEv3Family",
      "standardEv4Family",
      "standardFFamily",
      "standardFSFamily",
      "standardFSv2Family",
      "standardHFamily",
      "standardLSv2Family",
      "standardMDSmallv2Family",
      "standardMIDSmallv2Family",
      "standardMISmallv2Family",
      "standardMSFamily",
      "standardMSmallv2Family",
      "standardMSv2Family",
      "standardNCSv3Family",
      "standardNVFamily",
      "standardNVSv2Family",
      "standardNVSv3Family",
      "standardNVSv4Family",
      "standardXEIDSv4Family",
      "standardXEISv4Family"
    ]
  },
  {
    "Region": "centralus",
    "VmSkus": [
      "basicAFamily",
      "standardA0_A7Family",
      "standardAv2Family",
      "standardBSFamily",
      "standardDASv4Family",
      "standardDAv4Family",
      "standardDDSv4Family",
      "standardDDv4Family",
      "standardDFamily",
      "standardDSFamily",
      "standardDSv2Family",
      "standardDSv3Family",
      "standardDSv4Family",
      "standardDv2Family",
      "standardDv3Family",
      "standardDv4Family",
      "standardEASv4Family",
      "standardEAv4Family",
      "standardEDSv4Family",
      "standardEDv4Family",
      "standardEISv3Family",
      "standardEIv3Family",
      "standardESv3Family",
      "standardESv4Family",
      "standardEv3Family",
      "standardEv4Family",
      "standardFFamily",
      "standardFSFamily",
      "standardFSv2Family",
      "standardMDSmallv2Family",
      "standardMIDSmallv2Family",
      "standardMISmallv2Family",
      "standardMSFamily",
      "standardMSmallv2Family",
      "standardMSv2Family",
      "standardXEIDSv4Family",
      "standardXEISv4Family"
    ]
  },
  {
    "Region": "CentralUSEUAP",
    "VmSkus": [
      "basicAFamily",
      "standardA0_A7Family",
      "standardAv2Family",
      "standardBSFamily",
      "standardDCSv2Family",
      "standardDDSv4Family",
      "standardDDv4Family",
      "standardDFamily",
      "standardDSFamily",
      "standardDSv2Family",
      "standardDSv3Family",
      "standardDSv4Family",
      "standardDv2Family",
      "standardDv3Family",
      "standardDv4Family",
      "standardEDSv4Family",
      "standardEDv4Family",
      "standardEISv3Family",
      "standardEIv3Family",
      "standardESv3Family",
      "standardESv4Family",
      "standardEv3Family",
      "standardEv4Family",
      "standardFFamily",
      "standardFSFamily",
      "standardFSv2Family",
      "standardXEIDSv4Family",
      "standardXEISv4Family"
    ]
  },
  {
    "Region": "eastasia",
    "VmSkus": [
      "basicAFamily",
      "standardA0_A7Family",
      "standardAv2Family",
      "standardBSFamily",
      "standardDASv4Family",
      "standardDAv4Family",
      "standardDDSv4Family",
      "standardDDv4Family",
      "standardDFamily",
      "standardDSFamily",
      "standardDSv2Family",
      "standardDSv3Family",
      "standardDSv4Family",
      "standardDv2Family",
      "standardDv3Family",
      "standardDv4Family",
      "standardEASv4Family",
      "standardEAv4Family",
      "standardEDSv4Family",
      "standardEDv4Family",
      "standardEISv3Family",
      "standardEIv3Family",
      "standardESv3Family",
      "standardESv4Family",
      "standardEv3Family",
      "standardEv4Family",
      "standardFFamily",
      "standardFSFamily",
      "standardFSv2Family",
      "standardMSFamily",
      "standardXEIDSv4Family",
      "standardXEISv4Family"
    ]
  },
  {
    "Region": "eastus",
    "VmSkus": [
      "basicAFamily",
      "Standard NCASv3_T4 Family",
      "standardA0_A7Family",
      "standardA8_A11Family",
      "standardAv2Family",
      "standardBSFamily",
      "standardDASv4Family",
      "standardDAv4Family",
      "standardDCSFamily",
      "standardDCSv2Family",
      "standardDDSv4Family",
      "standardDDv4Family",
      "standardDFamily",
      "standardDSFamily",
      "standardDSv2Family",
      "standardDSv3Family",
      "standardDSv4Family",
      "standardDv2Family",
      "standardDv3Family",
      "standardDv4Family",
      "standardEASv4Family",
      "standardEAv4Family",
      "standardEDSv4Family",
      "standardEDv4Family",
      "standardEISv3Family",
      "standardEIv3Family",
      "standardESv3Family",
      "standardESv4Family",
      "standardEv3Family",
      "standardEv4Family",
      "standardFFamily",
      "standardFSFamily",
      "standardFSv2Family",
      "standardHBrsv2Family",
      "standardHBSFamily",
      "standardHCSFamily",
      "standardHFamily",
      "standardLSv2Family",
      "standardMDSmallv2Family",
      "standardMIDSmallv2Family",
      "standardMISmallv2Family",
      "standardMSFamily",
      "standardMSmallv2Family",
      "standardMSv2Family",
      "standardNCFamily",
      "standardNCSv2Family",
      "standardNCSv3Family",
      "standardNDSFamily",
      "standardNDSv2Family",
      "standardNDSv3Family",
      "standardNPSFamily",
      "standardNVFamily",
      "standardNVSv2Family",
      "standardNVSv3Family",
      "standardNVSv4Family",
      "standardPBSFamily",
      "standardXEIDSv4Family",
      "standardXEISv4Family"
    ]
  },
  {
    "Region": "eastus2",
    "VmSkus": [
      "basicAFamily",
      "Standard NCASv3_T4 Family",
      "standardA0_A7Family",
      "standardAv2Family",
      "standardBSFamily",
      "standardDASv4Family",
      "standardDAv4Family",
      "standardDDSv4Family",
      "standardDDv4Family",
      "standardDFamily",
      "standardDSFamily",
      "standardDSv2Family",
      "standardDSv3Family",
      "standardDSv4Family",
      "standardDv2Family",
      "standardDv3Family",
      "standardDv4Family",
      "standardEASv4Family",
      "standardEAv4Family",
      "standardEDSv4Family",
      "standardEDv4Family",
      "standardEISv3Family",
      "standardEIv3Family",
      "standardESv3Family",
      "standardESv4Family",
      "standardEv3Family",
      "standardEv4Family",
      "standardFFamily",
      "standardFSFamily",
      "standardFSv2Family",
      "standardGFamily",
      "standardGSFamily",
      "standardLSFamily",
      "standardLSv2Family",
      "standardMDSmallv2Family",
      "standardMIDSmallv2Family",
      "standardMISmallv2Family",
      "standardMSFamily",
      "standardMSmallv2Family",
      "standardMSv2Family",
      "standardNCFamily",
      "standardNCSv3Family",
      "standardNVFamily",
      "standardNVSv2Family",
      "standardNVSv3Family",
      "standardNVSv4Family",
      "standardXEIDSv4Family",
      "standardXEISv4Family"
    ]
  },
  {
    "Region": "EastUS2EUAP",
    "VmSkus": [
      "basicAFamily",
      "standardA0_A7Family",
      "standardAv2Family",
      "standardBSFamily",
      "standardDASv4Family",
      "standardDAv4Family",
      "standardDDSv4Family",
      "standardDDv4Family",
      "standardDSv2Family",
      "standardDSv3Family",
      "standardDSv4Family",
      "standardDv2Family",
      "standardDv3Family",
      "standardDv4Family",
      "standardEASv4Family",
      "standardEAv4Family",
      "standardEDSv4Family",
      "standardEDv4Family",
      "standardEISv3Family",
      "standardEIv3Family",
      "standardESv3Family",
      "standardESv4Family",
      "standardEv3Family",
      "standardEv4Family",
      "standardFFamily",
      "standardFSFamily",
      "standardFSv2Family",
      "standardMDSmallv2Family",
      "standardMIDSmallv2Family",
      "standardMISmallv2Family",
      "standardMSFamily",
      "standardMSmallv2Family",
      "standardMSv2Family",
      "standardNDSFamily",
      "standardXEIDSv4Family",
      "standardXEISv4Family"
    ]
  },
  {
    "Region": "FranceCentral",
    "VmSkus": [
      "basicAFamily",
      "standardA0_A7Family",
      "standardAv2Family",
      "standardBSFamily",
      "standardDDSv4Family",
      "standardDDv4Family",
      "standardDSv2Family",
      "standardDSv3Family",
      "standardDSv4Family",
      "standardDv2Family",
      "standardDv3Family",
      "standardDv4Family",
      "standardEDSv4Family",
      "standardEDv4Family",
      "standardEISv3Family",
      "standardEIv3Family",
      "standardESv3Family",
      "standardESv4Family",
      "standardEv3Family",
      "standardEv4Family",
      "standardFFamily",
      "standardFSFamily",
      "standardFSv2Family",
      "standardMDSmallv2Family",
      "standardMIDSmallv2Family",
      "standardMISmallv2Family",
      "standardMSFamily",
      "standardMSmallv2Family",
      "standardNCSv3Family",
      "standardNVSv2Family",
      "standardNVSv3Family",
      "standardXEIDSv4Family",
      "standardXEISv4Family"
    ]
  },
  {
    "Region": "FranceSouth",
    "VmSkus": [
      "basicAFamily",
      "standardA0_A7Family",
      "standardAv2Family",
      "standardBSFamily",
      "standardDDSv4Family",
      "standardDDv4Family",
      "standardDSv2Family",
      "standardDSv3Family",
      "standardDSv4Family",
      "standardDv2Family",
      "standardDv3Family",
      "standardDv4Family",
      "standardEDSv4Family",
      "standardEDv4Family",
      "standardEISv3Family",
      "standardEIv3Family",
      "standardESv3Family",
      "standardESv4Family",
      "standardEv3Family",
      "standardEv4Family",
      "standardFFamily",
      "standardFSFamily",
      "standardFSv2Family",
      "standardXEIDSv4Family",
      "standardXEISv4Family"
    ]
  },
  {
    "Region": "GermanyNorth",
    "VmSkus": [
      "standardAv2Family",
      "standardBSFamily",
      "standardDSv2Family",
      "standardDSv3Family",
      "standardDv2Family",
      "standardDv3Family",
      "standardEISv3Family",
      "standardEIv3Family",
      "standardESv3Family",
      "standardEv3Family",
      "standardFFamily",
      "standardFSFamily",
      "standardMSFamily"
    ]
  },
  {
    "Region": "GermanyWestCentral",
    "VmSkus": [
      "standardAv2Family",
      "standardBSFamily",
      "standardDDSv4Family",
      "standardDDv4Family",
      "standardDSv2Family",
      "standardDSv3Family",
      "standardDSv4Family",
      "standardDv2Family",
      "standardDv3Family",
      "standardDv4Family",
      "standardEDSv4Family",
      "standardEDv4Family",
      "standardEISv3Family",
      "standardEIv3Family",
      "standardESv3Family",
      "standardESv4Family",
      "standardEv3Family",
      "standardEv4Family",
      "standardFFamily",
      "standardFSFamily",
      "standardFSv2Family",
      "standardMDSmallv2Family",
      "standardMIDSmallv2Family",
      "standardMISmallv2Family",
      "standardMSFamily",
      "standardMSmallv2Family",
      "standardMSv2Family",
      "standardXEIDSv4Family",
      "standardXEISv4Family"
    ]
  },
  {
    "Region": "japaneast",
    "VmSkus": [
      "basicAFamily",
      "Standard NCASv3_T4 Family",
      "standardA0_A7Family",
      "standardAv2Family",
      "standardBSFamily",
      "standardDASv4Family",
      "standardDAv4Family",
      "standardDDSv4Family",
      "standardDDv4Family",
      "standardDFamily",
      "standardDSFamily",
      "standardDSv2Family",
      "standardDSv3Family",
      "standardDSv4Family",
      "standardDv2Family",
      "standardDv3Family",
      "standardDv4Family",
      "standardEASv4Family",
      "standardEAv4Family",
      "standardEDSv4Family",
      "standardEDv4Family",
      "standardEISv3Family",
      "standardEIv3Family",
      "standardESv3Family",
      "standardESv4Family",
      "standardEv3Family",
      "standardEv4Family",
      "standardFFamily",
      "standardFSFamily",
      "standardFSv2Family",
      "standardGFamily",
      "standardGSFamily",
      "standardHBrsv2Family",
      "standardHCSFamily",
      "standardHFamily",
      "standardLSFamily",
      "standardLSv2Family",
      "standardMDSmallv2Family",
      "standardMIDSmallv2Family",
      "standardMISmallv2Family",
      "standardMSFamily",
      "standardMSmallv2Family",
      "standardMSv2Family",
      "standardNCSv3Family",
      "standardNVFamily",
      "standardNVSv2Family",
      "standardNVSv3Family",
      "standardNVSv4Family",
      "standardXEIDSv4Family",
      "standardXEISv4Family"
    ]
  },
  {
    "Region": "japanwest",
    "VmSkus": [
      "basicAFamily",
      "standardA0_A7Family",
      "standardAv2Family",
      "standardBSFamily",
      "standardDDSv4Family",
      "standardDDv4Family",
      "standardDFamily",
      "standardDSFamily",
      "standardDSv2Family",
      "standardDSv3Family",
      "standardDSv4Family",
      "standardDv2Family",
      "standardDv3Family",
      "standardDv4Family",
      "standardEDSv4Family",
      "standardEDv4Family",
      "standardEISv3Family",
      "standardEIv3Family",
      "standardESv3Family",
      "standardESv4Family",
      "standardEv3Family",
      "standardEv4Family",
      "standardFFamily",
      "standardFSFamily",
      "standardFSv2Family",
      "standardMSFamily",
      "standardMSv2Family",
      "standardXEIDSv4Family",
      "standardXEISv4Family"
    ]
  },
  {
    "Region": "KoreaCentral",
    "VmSkus": [
      "basicAFamily",
      "Standard NCASv3_T4 Family",
      "standardA0_A7Family",
      "standardAv2Family",
      "standardBSFamily",
      "standardDASv4Family",
      "standardDAv4Family",
      "standardDDSv4Family",
      "standardDDv4Family",
      "standardDSv2Family",
      "standardDSv3Family",
      "standardDSv4Family",
      "standardDv2Family",
      "standardDv3Family",
      "standardDv4Family",
      "standardEASv4Family",
      "standardEAv4Family",
      "standardEDSv4Family",
      "standardEDv4Family",
      "standardEISv3Family",
      "standardEIv3Family",
      "standardESv3Family",
      "standardESv4Family",
      "standardEv3Family",
      "standardEv4Family",
      "standardFFamily",
      "standardFSFamily",
      "standardFSv2Family",
      "standardHCSFamily",
      "standardMSFamily",
      "standardMSv2Family",
      "standardNCSv3Family",
      "standardXEIDSv4Family",
      "standardXEISv4Family"
    ]
  },
  {
    "Region": "KoreaSouth",
    "VmSkus": [
      "basicAFamily",
      "standardA0_A7Family",
      "standardAv2Family",
      "standardBSFamily",
      "standardDDSv4Family",
      "standardDDv4Family",
      "standardDSv2Family",
      "standardDSv3Family",
      "standardDSv4Family",
      "standardDv2Family",
      "standardDv3Family",
      "standardDv4Family",
      "standardEDSv4Family",
      "standardEDv4Family",
      "standardEISv3Family",
      "standardEIv3Family",
      "standardESv3Family",
      "standardESv4Family",
      "standardEv3Family",
      "standardEv4Family",
      "standardFFamily",
      "standardFSFamily",
      "standardFSv2Family",
      "standardMSFamily",
      "standardMSv2Family",
      "standardXEIDSv4Family",
      "standardXEISv4Family"
    ]
  },
  {
    "Region": "northcentralus",
    "VmSkus": [
      "basicAFamily",
      "standardA0_A7Family",
      "standardA8_A11Family",
      "standardAv2Family",
      "standardBSFamily",
      "standardDASv4Family",
      "standardDAv4Family",
      "standardDDSv4Family",
      "standardDDv4Family",
      "standardDFamily",
      "standardDSFamily",
      "standardDSv2Family",
      "standardDSv3Family",
      "standardDSv4Family",
      "standardDv2Family",
      "standardDv3Family",
      "standardDv4Family",
      "standardEASv4Family",
      "standardEAv4Family",
      "standardEDSv4Family",
      "standardEDv4Family",
      "standardEISv3Family",
      "standardEIv3Family",
      "standardESv3Family",
      "standardESv4Family",
      "standardEv3Family",
      "standardEv4Family",
      "standardFFamily",
      "standardFSFamily",
      "standardFSv2Family",
      "standardHFamily",
      "standardMDSmallv2Family",
      "standardMIDSmallv2Family",
      "standardMISmallv2Family",
      "standardMSFamily",
      "standardMSmallv2Family",
      "standardMSv2Family",
      "standardNCFamily",
      "standardNVFamily",
      "standardNVSv4Family",
      "standardXEIDSv4Family",
      "standardXEISv4Family"
    ]
  },
  {
    "Region": "northeurope",
    "VmSkus": [
      "basicAFamily",
      "Standard NCASv3_T4 Family",
      "standardA0_A7Family",
      "standardA8_A11Family",
      "standardAv2Family",
      "standardBSFamily",
      "standardDASv4Family",
      "standardDAv4Family",
      "standardDCSv2Family",
      "standardDDSv4Family",
      "standardDDv4Family",
      "standardDFamily",
      "standardDSFamily",
      "standardDSv2Family",
      "standardDSv3Family",
      "standardDSv4Family",
      "standardDv2Family",
      "standardDv3Family",
      "standardDv4Family",
      "standardEASv4Family",
      "standardEAv4Family",
      "standardEDSv4Family",
      "standardEDv4Family",
      "standardEISv3Family",
      "standardEIv3Family",
      "standardESv3Family",
      "standardESv4Family",
      "standardEv3Family",
      "standardEv4Family",
      "standardFFamily",
      "standardFSFamily",
      "standardFSv2Family",
      "standardHCSFamily",
      "standardHFamily",
      "standardLSv2Family",
      "standardMDSmallv2Family",
      "standardMIDSmallv2Family",
      "standardMISmallv2Family",
      "standardMSFamily",
      "standardMSmallv2Family",
      "standardMSv2Family",
      "standardNCFamily",
      "standardNCSv3Family",
      "standardNVFamily",
      "standardNVSv2Family",
      "standardNVSv3Family",
      "standardNVSv4Family",
      "standardXEIDSv4Family",
      "standardXEISv4Family"
    ]
  },
  {
    "Region": "NorwayEast",
    "VmSkus": [
      "standardAv2Family",
      "standardBSFamily",
      "standardDDSv4Family",
      "standardDDv4Family",
      "standardDSv2Family",
      "standardDSv3Family",
      "standardDSv4Family",
      "standardDv2Family",
      "standardDv3Family",
      "standardDv4Family",
      "standardEDSv4Family",
      "standardEDv4Family",
      "standardEISv3Family",
      "standardEIv3Family",
      "standardESv3Family",
      "standardESv4Family",
      "standardEv3Family",
      "standardEv4Family",
      "standardFFamily",
      "standardFSFamily",
      "standardFSv2Family",
      "standardMDSmallv2Family",
      "standardMIDSmallv2Family",
      "standardMISmallv2Family",
      "standardMSFamily",
      "standardMSmallv2Family",
      "standardXEIDSv4Family",
      "standardXEISv4Family"
    ]
  },
  {
    "Region": "NorwayWest",
    "VmSkus": [
      "standardAv2Family",
      "standardBSFamily",
      "standardDSv2Family",
      "standardDSv3Family",
      "standardDv2Family",
      "standardDv3Family",
      "standardEISv3Family",
      "standardEIv3Family",
      "standardESv3Family",
      "standardEv3Family",
      "standardFFamily",
      "standardFSFamily",
      "standardNVSv2Family",
      "standardNVSv3Family"
    ]
  },
  {
    "Region": "SouthAfricaNorth",
    "VmSkus": [
      "basicAFamily",
      "standardA0_A7Family",
      "standardAv2Family",
      "standardBSFamily",
      "standardDDSv4Family",
      "standardDDv4Family",
      "standardDSv2Family",
      "standardDSv3Family",
      "standardDSv4Family",
      "standardDv2Family",
      "standardDv3Family",
      "standardDv4Family",
      "standardEDSv4Family",
      "standardEDv4Family",
      "standardEISv3Family",
      "standardEIv3Family",
      "standardESv3Family",
      "standardESv4Family",
      "standardEv3Family",
      "standardEv4Family",
      "standardFFamily",
      "standardFSFamily",
      "standardFSv2Family",
      "standardMSFamily",
      "standardNVSv2Family",
      "standardNVSv3Family",
      "standardXEIDSv4Family",
      "standardXEISv4Family"
    ]
  },
  {
    "Region": "SouthAfricaWest",
    "VmSkus": [
      "basicAFamily",
      "standardA0_A7Family",
      "standardAv2Family",
      "standardBSFamily",
      "standardDSv2Family",
      "standardDSv3Family",
      "standardDv2Family",
      "standardDv3Family",
      "standardEISv3Family",
      "standardEIv3Family",
      "standardESv3Family",
      "standardEv3Family",
      "standardFFamily",
      "standardFSFamily",
      "standardMSFamily"
    ]
  },
  {
    "Region": "southcentralus",
    "VmSkus": [
      "basicAFamily",
      "Standard NCASv3_T4 Family",
      "standardA0_A7Family",
      "standardA8_A11Family",
      "standardAv2Family",
      "standardBSFamily",
      "standardDASv4Family",
      "standardDAv4Family",
      "standardDCSv2Family",
      "standardDDSv4Family",
      "standardDDv4Family",
      "standardDFamily",
      "standardDSFamily",
      "standardDSv2Family",
      "standardDSv3Family",
      "standardDSv4Family",
      "standardDv2Family",
      "standardDv3Family",
      "standardDv4Family",
      "standardEASv4Family",
      "standardEAv4Family",
      "standardEDSv4Family",
      "standardEDv4Family",
      "standardEISv3Family",
      "standardEIv3Family",
      "standardESv3Family",
      "standardESv4Family",
      "standardEv3Family",
      "standardEv4Family",
      "standardFFamily",
      "standardFSFamily",
      "standardFSv2Family",
      "standardHBrsv2Family",
      "standardHBSFamily",
      "standardHCSFamily",
      "standardHFamily",
      "standardLSv2Family",
      "standardMDSmallv2Family",
      "standardMIDSmallv2Family",
      "standardMISmallv2Family",
      "standardMSFamily",
      "standardMSmallv2Family",
      "standardMSv2Family",
      "standardNCFamily",
      "standardNCSv2Family",
      "standardNCSv3Family",
      "standardNDSv2Family",
      "standardNVFamily",
      "standardNVSv2Family",
      "standardNVSv3Family",
      "standardNVSv4Family",
      "standardXEIDSv4Family",
      "standardXEISv4Family"
    ]
  },
  {
    "Region": "southeastasia",
    "VmSkus": [
      "basicAFamily",
      "Standard NCASv3_T4 Family",
      "standardA0_A7Family",
      "standardAv2Family",
      "standardBSFamily",
      "standardDASv4Family",
      "standardDAv4Family",
      "standardDCSv2Family",
      "standardDDSv4Family",
      "standardDDv4Family",
      "standardDFamily",
      "standardDSFamily",
      "standardDSv2Family",
      "standardDSv3Family",
      "standardDSv4Family",
      "standardDv2Family",
      "standardDv3Family",
      "standardDv4Family",
      "standardEASv4Family",
      "standardEAv4Family",
      "standardEDSv4Family",
      "standardEDv4Family",
      "standardEISv3Family",
      "standardEIv3Family",
      "standardESv3Family",
      "standardESv4Family",
      "standardEv3Family",
      "standardEv4Family",
      "standardFFamily",
      "standardFSFamily",
      "standardFSv2Family",
      "standardGFamily",
      "standardGSFamily",
      "standardHCSFamily",
      "standardHFamily",
      "standardLSFamily",
      "standardLSv2Family",
      "standardMDSmallv2Family",
      "standardMIDSmallv2Family",
      "standardMISmallv2Family",
      "standardMSFamily",
      "standardMSmallv2Family",
      "standardMSv2Family",
      "standardNCSv2Family",
      "standardNCSv3Family",
      "standardNDSFamily",
      "standardNPSFamily",
      "standardNVFamily",
      "standardNVSv2Family",
      "standardNVSv3Family",
      "standardNVSv4Family",
      "standardPBSFamily",
      "standardXEIDSv4Family",
      "standardXEISv4Family"
    ]
  },
  {
    "Region": "SouthIndia",
    "VmSkus": [
      "basicAFamily",
      "standardA0_A7Family",
      "standardAv2Family",
      "standardBSFamily",
      "standardDSv2Family",
      "standardDSv3Family",
      "standardDv2Family",
      "standardDv3Family",
      "standardEISv3Family",
      "standardEIv3Family",
      "standardESv3Family",
      "standardEv3Family",
      "standardFFamily",
      "standardFSFamily",
      "standardFSv2Family",
      "standardMSFamily"
    ]
  },
  {
    "Region": "SwitzerlandNorth",
    "VmSkus": [
      "standardAv2Family",
      "standardBSFamily",
      "standardDDSv4Family",
      "standardDDv4Family",
      "standardDSv2Family",
      "standardDSv3Family",
      "standardDSv4Family",
      "standardDv2Family",
      "standardDv3Family",
      "standardDv4Family",
      "standardEDSv4Family",
      "standardEDv4Family",
      "standardEISv3Family",
      "standardEIv3Family",
      "standardESv3Family",
      "standardESv4Family",
      "standardEv3Family",
      "standardEv4Family",
      "standardFFamily",
      "standardFSFamily",
      "standardFSv2Family",
      "standardMSFamily",
      "standardXEIDSv4Family",
      "standardXEISv4Family"
    ]
  },
  {
    "Region": "SwitzerlandWest",
    "VmSkus": [
      "standardAv2Family",
      "standardBSFamily",
      "standardDSv2Family",
      "standardDSv3Family",
      "standardDv2Family",
      "standardDv3Family",
      "standardEISv3Family",
      "standardEIv3Family",
      "standardESv3Family",
      "standardEv3Family",
      "standardFFamily",
      "standardFSFamily",
      "standardMSFamily"
    ]
  },
  {
    "Region": "UAECentral",
    "VmSkus": [
      "basicAFamily",
      "standardA0_A7Family",
      "standardAv2Family",
      "standardBSFamily",
      "standardDDSv4Family",
      "standardDDv4Family",
      "standardDSv2Family",
      "standardDSv3Family",
      "standardDSv4Family",
      "standardDv2Family",
      "standardDv3Family",
      "standardDv4Family",
      "standardEDSv4Family",
      "standardEDv4Family",
      "standardEISv3Family",
      "standardEIv3Family",
      "standardESv3Family",
      "standardESv4Family",
      "standardEv3Family",
      "standardEv4Family",
      "standardFFamily",
      "standardFSFamily",
      "standardFSv2Family",
      "standardMDSmallv2Family",
      "standardMIDSmallv2Family",
      "standardMISmallv2Family",
      "standardMSFamily",
      "standardMSmallv2Family",
      "standardMSv2Family",
      "standardXEIDSv4Family",
      "standardXEISv4Family"
    ]
  },
  {
    "Region": "UAENorth",
    "VmSkus": [
      "basicAFamily",
      "standardA0_A7Family",
      "standardAv2Family",
      "standardBSFamily",
      "standardDDSv4Family",
      "standardDDv4Family",
      "standardDSv2Family",
      "standardDSv3Family",
      "standardDSv4Family",
      "standardDv2Family",
      "standardDv3Family",
      "standardDv4Family",
      "standardEDSv4Family",
      "standardEDv4Family",
      "standardEISv3Family",
      "standardEIv3Family",
      "standardESv3Family",
      "standardESv4Family",
      "standardEv3Family",
      "standardEv4Family",
      "standardFFamily",
      "standardFSFamily",
      "standardFSv2Family",
      "standardHBrsv2Family",
      "standardMDSmallv2Family",
      "standardMIDSmallv2Family",
      "standardMISmallv2Family",
      "standardMSFamily",
      "standardMSmallv2Family",
      "standardMSv2Family",
      "standardNVSv2Family",
      "standardNVSv3Family",
      "standardXEIDSv4Family",
      "standardXEISv4Family"
    ]
  },
  {
    "Region": "uksouth",
    "VmSkus": [
      "basicAFamily",
      "Standard NCASv3_T4 Family",
      "standardA0_A7Family",
      "standardAv2Family",
      "standardBSFamily",
      "standardDASv4Family",
      "standardDAv4Family",
      "standardDCSv2Family",
      "standardDDSv4Family",
      "standardDDv4Family",
      "standardDSv2Family",
      "standardDSv3Family",
      "standardDSv4Family",
      "standardDv2Family",
      "standardDv3Family",
      "standardDv4Family",
      "standardEASv4Family",
      "standardEAv4Family",
      "standardEDSv4Family",
      "standardEDv4Family",
      "standardEISv3Family",
      "standardEIv3Family",
      "standardESv3Family",
      "standardESv4Family",
      "standardEv3Family",
      "standardEv4Family",
      "standardFFamily",
      "standardFSFamily",
      "standardFSv2Family",
      "standardGFamily",
      "standardGSFamily",
      "standardHFamily",
      "standardLSFamily",
      "standardLSv2Family",
      "standardMDSmallv2Family",
      "standardMIDSmallv2Family",
      "standardMISmallv2Family",
      "standardMSFamily",
      "standardMSmallv2Family",
      "standardMSv2Family",
      "standardNCFamily",
      "standardNCSv3Family",
      "standardNVFamily",
      "standardNVSv2Family",
      "standardNVSv3Family",
      "standardNVSv4Family",
      "standardXEIDSv4Family",
      "standardXEISv4Family"
    ]
  },
  {
    "Region": "ukwest",
    "VmSkus": [
      "basicAFamily",
      "standardA0_A7Family",
      "standardAv2Family",
      "standardBSFamily",
      "standardDCSv2Family",
      "standardDDSv4Family",
      "standardDDv4Family",
      "standardDSv2Family",
      "standardDSv3Family",
      "standardDSv4Family",
      "standardDv2Family",
      "standardDv3Family",
      "standardDv4Family",
      "standardEDSv4Family",
      "standardEDv4Family",
      "standardEISv3Family",
      "standardEIv3Family",
      "standardESv3Family",
      "standardESv4Family",
      "standardEv3Family",
      "standardEv4Family",
      "standardFFamily",
      "standardFSFamily",
      "standardFSv2Family",
      "standardMSFamily",
      "standardXEIDSv4Family",
      "standardXEISv4Family"
    ]
  },
  {
    "Region": "westcentralus",
    "VmSkus": [
      "basicAFamily",
      "standardA0_A7Family",
      "standardAv2Family",
      "standardBSFamily",
      "standardDDSv4Family",
      "standardDDv4Family",
      "standardDSv2Family",
      "standardDSv3Family",
      "standardDSv4Family",
      "standardDv2Family",
      "standardDv3Family",
      "standardDv4Family",
      "standardEDSv4Family",
      "standardEDv4Family",
      "standardEISv3Family",
      "standardEIv3Family",
      "standardESv3Family",
      "standardESv4Family",
      "standardEv3Family",
      "standardEv4Family",
      "standardFFamily",
      "standardFSFamily",
      "standardFSv2Family",
      "standardXEIDSv4Family",
      "standardXEISv4Family"
    ]
  },
  {
    "Region": "westeurope",
    "VmSkus": [
      "basicAFamily",
      "Standard NCASv3_T4 Family",
      "standardA0_A7Family",
      "standardA8_A11Family",
      "standardAv2Family",
      "standardBSFamily",
      "standardDASv4Family",
      "standardDAv4Family",
      "standardDCSFamily",
      "standardDCSv2Family",
      "standardDDSv4Family",
      "standardDDv4Family",
      "standardDFamily",
      "standardDSFamily",
      "standardDSv2Family",
      "standardDSv3Family",
      "standardDSv4Family",
      "standardDv2Family",
      "standardDv3Family",
      "standardDv4Family",
      "standardEASv4Family",
      "standardEAv4Family",
      "standardEDSv4Family",
      "standardEDv4Family",
      "standardEISv3Family",
      "standardEIv3Family",
      "standardESv3Family",
      "standardESv4Family",
      "standardEv3Family",
      "standardEv4Family",
      "standardFFamily",
      "standardFSFamily",
      "standardFSv2Family",
      "standardGFamily",
      "standardGSFamily",
      "standardHBrsv2Family",
      "standardHBSFamily",
      "standardHCSFamily",
      "standardHFamily",
      "standardLSFamily",
      "standardLSv2Family",
      "standardMDSmallv2Family",
      "standardMIDSmallv2Family",
      "standardMISmallv2Family",
      "standardMSFamily",
      "standardMSmallv2Family",
      "standardMSv2Family",
      "standardNCFamily",
      "standardNCSv2Family",
      "standardNCSv3Family",
      "standardNDSFamily",
      "standardNDSv2Family",
      "standardNPSFamily",
      "standardNVFamily",
      "standardNVSv2Family",
      "standardNVSv3Family",
      "standardNVSv4Family",
      "standardPBSFamily",
      "standardXEIDSv4Family",
      "standardXEISv4Family"
    ]
  },
  {
    "Region": "WestIndia",
    "VmSkus": [
      "basicAFamily",
      "standardA0_A7Family",
      "standardAv2Family",
      "standardBSFamily",
      "standardDFamily",
      "standardDSFamily",
      "standardDSv2Family",
      "standardDSv3Family",
      "standardDv2Family",
      "standardDv3Family",
      "standardEISv3Family",
      "standardEIv3Family",
      "standardESv3Family",
      "standardEv3Family",
      "standardFFamily",
      "standardFSFamily",
      "standardFSv2Family"
    ]
  },
  {
    "Region": "westus",
    "VmSkus": [
      "basicAFamily",
      "Standard NCASv3_T4 Family",
      "standardA0_A7Family",
      "standardA8_A11Family",
      "standardAv2Family",
      "standardBSFamily",
      "standardDASv4Family",
      "standardDAv4Family",
      "standardDCSv2Family",
      "standardDDSv4Family",
      "standardDDv4Family",
      "standardDFamily",
      "standardDSFamily",
      "standardDSv2Family",
      "standardDSv3Family",
      "standardDSv4Family",
      "standardDv2Family",
      "standardDv3Family",
      "standardDv4Family",
      "standardEASv4Family",
      "standardEAv4Family",
      "standardEDSv4Family",
      "standardEDv4Family",
      "standardEISv3Family",
      "standardEIv3Family",
      "standardESv3Family",
      "standardESv4Family",
      "standardEv3Family",
      "standardEv4Family",
      "standardFFamily",
      "standardFSFamily",
      "standardFSv2Family",
      "standardGFamily",
      "standardGSFamily",
      "standardHFamily",
      "standardLSFamily",
      "standardLSv2Family",
      "standardMDSmallv2Family",
      "standardMIDSmallv2Family",
      "standardMISmallv2Family",
      "standardMSFamily",
      "standardMSmallv2Family",
      "standardMSv2Family",
      "standardNCSv3Family",
      "standardNVSv2Family",
      "standardNVSv3Family",
      "standardNVSv4Family",
      "standardXEIDSv4Family",
      "standardXEISv4Family"
    ]
  },
  {
    "Region": "westus2",
    "VmSkus": [
      "basicAFamily",
      "Standard NCASv3_T4 Family",
      "standardA0_A7Family",
      "standardAv2Family",
      "standardBSFamily",
      "standardDASv4Family",
      "standardDAv4Family",
      "standardDCSv2Family",
      "standardDDSv4Family",
      "standardDDv4Family",
      "standardDSv2Family",
      "standardDSv3Family",
      "standardDSv4Family",
      "standardDv2Family",
      "standardDv3Family",
      "standardDv4Family",
      "standardEASv4Family",
      "standardEAv4Family",
      "standardEDSv4Family",
      "standardEDv4Family",
      "standardEISv3Family",
      "standardEIv3Family",
      "standardESv3Family",
      "standardESv4Family",
      "standardEv3Family",
      "standardEv4Family",
      "standardFFamily",
      "standardFSFamily",
      "standardFSv2Family",
      "standardGFamily",
      "standardGSFamily",
      "standardHBrsv2Family",
      "standardHCSFamily",
      "standardHFamily",
      "standardLSFamily",
      "standardLSv2Family",
      "standardMDSmallv2Family",
      "standardMIDSmallv2Family",
      "standardMISmallv2Family",
      "standardMSFamily",
      "standardMSmallv2Family",
      "standardMSv2Family",
      "standardNCFamily",
      "standardNCSv2Family",
      "standardNCSv3Family",
      "standardNDSFamily",
      "standardNDSv2Family",
      "standardNPSFamily",
      "standardNVFamily",
      "standardNVSv2Family",
      "standardNVSv3Family",
      "standardNVSv4Family",
      "standardPBSFamily",
      "standardXEIDSv4Family",
      "standardXEISv4Family"
    ]
  },
  {
    "Region": "WestUS3",
    "VmSkus": [
      "standardAv2Family",
      "standardBSFamily",
      "standardDDSv4Family",
      "standardDDv4Family",
      "standardDSv2Family",
      "standardDSv3Family",
      "standardDSv4Family",
      "standardDv2Family",
      "standardDv3Family",
      "standardDv4Family",
      "standardEDSv4Family",
      "standardEDv4Family",
      "standardESv3Family",
      "standardESv4Family",
      "standardEv3Family",
      "standardEv4Family",
      "standardFFamily",
      "standardFSFamily",
      "standardFSv2Family",
      "standardXEIDSv4Family",
      "standardXEISv4Family"
    ]
  }
]